<annotation>
	<folder></folder>
	<filename>tl_94_jpg.rf.dce75844db410aaeb64e0b752f44b1e1.jpg</filename>
	<path>tl_94_jpg.rf.dce75844db410aaeb64e0b752f44b1e1.jpg</path>
	<source>
		<database>roboflow.ai</database>
	</source>
	<size>
		<width>416</width>
		<height>416</height>
		<depth>3</depth>
	</size>
	<segmented>0</segmented>
	<object>
		<name>thanhlong</name>
		<pose>Unspecified</pose>
		<truncated>0</truncated>
		<difficult>0</difficult>
		<occluded>0</occluded>
		<bndbox>
			<xmin>37</xmin>
			<xmax>350</xmax>
			<ymin>42</ymin>
			<ymax>291</ymax>
		</bndbox>
	</object>
</annotation>
